LICENSE
MANIFEST.in
README.md
setup.py
examples/datacenter_example.py
examples/image_examples.py
examples/ipblock_examples.py
examples/lan_example.py
examples/nic_examples.py
examples/pb_addNewServer.py
examples/pb_controlServerState.py
examples/pb_createDatacenter.py
examples/pb_datacenter_inventory.py
examples/pb_deleteServer.py
examples/pb_importVM.py
examples/pb_snapshotDatacenter.py
examples/server_example.py
examples/snapshot_examples.py
examples/user_management_examples.py
examples/volume_example.py
profitbricks/__init__.py
profitbricks/client.py
profitbricks/errors.py
profitbricks/utils.py
profitbricks.egg-info/PKG-INFO
profitbricks.egg-info/SOURCES.txt
profitbricks.egg-info/dependency_links.txt
profitbricks.egg-info/requires.txt
profitbricks.egg-info/top_level.txt
tests/__init__.py
tests/test_contract_resources.py
tests/test_datacenter.py
tests/test_errors.py
tests/test_firewall.py
tests/test_image.py
tests/test_ipblock.py
tests/test_lan.py
tests/test_loadbalancer.py
tests/test_location.py
tests/test_nic.py
tests/test_request.py
tests/test_server.py
tests/test_snapshot.py
tests/test_user_management.py
tests/test_volume.py