Metadata-Version: 2.1
Name: profitbricks
Version: 4.1.3
Summary: ProfitBricks API Client Library for Python
Home-page: https://github.com/profitbricks/profitbricks-sdk-python
Author: Matt Baldwin (stackpointcloud.com)
Author-email: baldwin@stackpointcloud.com
License: Apache 2.0
Keywords: profitbricks api client cloud
Platform: any
Classifier: Development Status :: 5 - Production/Stable
Classifier: Natural Language :: English
Classifier: Environment :: Web Environment
Classifier: Intended Audience :: Developers
Classifier: License :: OSI Approved :: Apache Software License
Classifier: Operating System :: POSIX
Classifier: Programming Language :: Python
Classifier: Programming Language :: Python :: 2
Classifier: Programming Language :: Python :: 3
Classifier: Topic :: Software Development :: Libraries :: Python Modules
Classifier: Topic :: Software Development :: Libraries :: Application Frameworks
Classifier: Topic :: Internet :: WWW/HTTP
Provides-Extra: testing
